snom_analysis/__init__.py
snom_analysis/main.py
snom_analysis/lib/__init__.py
snom_analysis/lib/additional_functions.py
snom_analysis/lib/data_range_selector.py
snom_analysis/lib/definitions.py
snom_analysis/lib/edge_detection.py
snom_analysis/lib/file_handling.py
snom_analysis/lib/height_masking.py
snom_analysis/lib/phase_analysis.py
snom_analysis/lib/phase_slider.py
snom_analysis/lib/profile.py
snom_analysis/lib/profile_selector.py
snom_analysis/lib/realign.py
snom_analysis/lib/rectangle_selector.py
snom_analysis/lib/snom_colormaps.py
snom_analysis-0.1.28.dist-info/licenses/LICENSE.txt
snom_analysis-0.1.28.dist-info/METADATA
snom_analysis-0.1.28.dist-info/WHEEL
snom_analysis-0.1.28.dist-info/top_level.txt
snom_analysis-0.1.28.dist-info/RECORD
