Metadata-Version: 2.4
Name: snom_analysis
Version: 0.1.28
Summary: Package for displaying and manipulating SNOM and AFM data
Author-email: "H.-J. Schill" <hajo.schill@acetovit.de>
Maintainer-email: "H.-J. Schill" <hajo.schill@acetovit.de>
License: GPL-3.0-or-later
Project-URL: Source, https://github.com/Hajo376/SNOM_AFM_analysis/
Project-URL: Documentation, https://snom-analysis.readthedocs.io/en/latest/index.html
Keywords: snom,afm,near-field,atomic force microscopy
Classifier: Development Status :: 4 - Beta
Classifier: Intended Audience :: Science/Research
Classifier: Programming Language :: Python :: 3 :: Only
Requires-Python: >=3.9
License-File: LICENSE.txt
Requires-Dist: scipy>=1.15.2
Requires-Dist: matplotlib>=3.10.1
Requires-Dist: mpl_point_clicker>=0.4.1
Requires-Dist: matplotlib-scalebar>=0.9.0
Requires-Dist: imageio>=2.37.0
Requires-Dist: colorcet>=3.1.0
Requires-Dist: scikit-image>=0.25.2
Dynamic: license-file
